phonepe/__init__.py
phonepe/main.py
phonepe-1.0.1.dist-info/METADATA
phonepe-1.0.1.dist-info/WHEEL
phonepe-1.0.1.dist-info/top_level.txt
phonepe-1.0.1.dist-info/RECORD
