Metadata-Version: 2.1
Name: phonepe
Version: 1.0.1
Summary: A Python library for interacting with PhonePe Payment Gateway API.
Home-page: https://github.com/devbijay/phonepe-pg
Author: Bijay Nayak
Author-email: bijay6779@gmail.com
Classifier: Development Status :: 5 - Production/Stable
Classifier: Intended Audience :: Developers
Classifier: Programming Language :: Python :: 3
Classifier: Operating System :: Unix
Classifier: Operating System :: MacOS :: MacOS X
Classifier: Operating System :: Microsoft :: Windows
